[
    {
        "ID": 0,
        "elevels": [
            1,
            1,
            1,
            1
        ],
        "epow": [
            100,
            100,
            100,
            100
        ],
        "eres": [
            100,
            100,
            100,
            100
        ]
    },
    {
        "ID": 1,
        "elevels": [
            1,
            1,
            1,
            1
        ],
        "epow": [
            80,
            80,
            80,
            80
        ],
        "eres": [
            72,
            72,
            72,
            72
        ]
    },
    {
        "ID": 2,
        "elevels": [
            1,
            1,
            1,
            1
        ],
        "epow": [
            80,
            80,
            80,
            80
        ],
        "eres": [
            90,
            90,
            90,
            90
        ]
    },
    {
        "ID": 3,
        "elevels": [
            1,
            0,
            0,
            0
        ],
        "epow": [
            100,
            80,
            70,
            80
        ],
        "eres": [
            48,
            48,
            25,
            72
        ]
    },
    {
        "ID": 4,
        "elevels": [
            1,
            0,
            0,
            0
        ],
        "epow": [
            100,
            80,
            70,
            80
        ],
        "eres": [
            72,
            72,
            25,
            127
        ]
    },
    {
        "ID": 5,
        "elevels": [
            1,
            0,
            0,
            0
        ],
        "epow": [
            95,
            85,
            90,
            85
        ],
        "eres": [
            48,
            48,
            25,
            48
        ]
    },
    {
        "ID": 6,
        "elevels": [
            1,
            0,
            0,
            0
        ],
        "epow": [
            95,
            85,
            90,
            85
        ],
        "eres": [
            72,
            72,
            48,
            100
        ]
    },
    {
        "ID": 7,
        "elevels": [
            2,
            1,
            0,
            0
        ],
        "epow": [
            105,
            100,
            80,
            70
        ],
        "eres": [
            48,
            100,
            7,
            72
        ]
    },
    {
        "ID": 8,
        "elevels": [
            2,
            1,
            0,
            0
        ],
        "epow": [
            105,
            100,
            80,
            70
        ],
        "eres": [
            72,
            175,
            25,
            100
        ]
    },
    {
        "ID": 9,
        "elevels": [
            1,
            0,
            0,
            2
        ],
        "epow": [
            90,
            90,
            95,
            105
        ],
        "eres": [
            100,
            48,
            48,
            7
        ]
    },
    {
        "ID": 10,
        "elevels": [
            1,
            0,
            0,
            2
        ],
        "epow": [
            90,
            90,
            95,
            105
        ],
        "eres": [
            152,
            72,
            72,
            25
        ]
    },
    {
        "ID": 11,
        "elevels": [
            1,
            1,
            1,
            2
        ],
        "epow": [
            95,
            95,
            95,
            110
        ],
        "eres": [
            127,
            72,
            48,
            7
        ]
    },
    {
        "ID": 12,
        "elevels": [
            1,
            1,
            1,
            2
        ],
        "epow": [
            95,
            95,
            95,
            110
        ],
        "eres": [
            175,
            100,
            72,
            25
        ]
    },
    {
        "ID": 13,
        "elevels": [
            2,
            1,
            0,
            0
        ],
        "epow": [
            100,
            95,
            80,
            80
        ],
        "eres": [
            25,
            72,
            7,
            48
        ]
    },
    {
        "ID": 14,
        "elevels": [
            2,
            1,
            0,
            0
        ],
        "epow": [
            100,
            95,
            80,
            80
        ],
        "eres": [
            25,
            127,
            72,
            48
        ]
    },
    {
        "ID": 15,
        "elevels": [
            0,
            1,
            1,
            2
        ],
        "epow": [
            100,
            95,
            95,
            95
        ],
        "eres": [
            48,
            100,
            72,
            7
        ]
    },
    {
        "ID": 16,
        "elevels": [
            0,
            1,
            1,
            2
        ],
        "epow": [
            100,
            95,
            95,
            95
        ],
        "eres": [
            72,
            152,
            100,
            25
        ]
    },
    {
        "ID": 17,
        "elevels": [
            2,
            1,
            1,
            1
        ],
        "epow": [
            100,
            100,
            100,
            95
        ],
        "eres": [
            48,
            100,
            100,
            127
        ]
    },
    {
        "ID": 18,
        "elevels": [
            4,
            2,
            2,
            0
        ],
        "epow": [
            110,
            95,
            95,
            90
        ],
        "eres": [
            152,
            100,
            100,
            48
        ]
    },
    {
        "ID": 19,
        "elevels": [
            2,
            4,
            0,
            2
        ],
        "epow": [
            95,
            115,
            85,
            95
        ],
        "eres": [
            100,
            175,
            25,
            100
        ]
    },
    {
        "ID": 20,
        "elevels": [
            2,
            0,
            4,
            2
        ],
        "epow": [
            95,
            85,
            115,
            95
        ],
        "eres": [
            100,
            25,
            175,
            100
        ]
    },
    {
        "ID": 21,
        "elevels": [
            0,
            2,
            2,
            4
        ],
        "epow": [
            90,
            95,
            95,
            110
        ],
        "eres": [
            48,
            100,
            100,
            152
        ]
    },
    {
        "ID": 22,
        "elevels": [
            6,
            2,
            2,
            0
        ],
        "epow": [
            120,
            95,
            95,
            80
        ],
        "eres": [
            100,
            48,
            48,
            7
        ]
    },
    {
        "ID": 23,
        "elevels": [
            6,
            2,
            2,
            0
        ],
        "epow": [
            120,
            95,
            95,
            80
        ],
        "eres": [
            193,
            100,
            100,
            25
        ]
    },
    {
        "ID": 24,
        "elevels": [
            2,
            6,
            0,
            2
        ],
        "epow": [
            95,
            125,
            75,
            95
        ],
        "eres": [
            48,
            127,
            7,
            48
        ]
    },
    {
        "ID": 25,
        "elevels": [
            2,
            6,
            0,
            2
        ],
        "epow": [
            95,
            125,
            75,
            95
        ],
        "eres": [
            100,
            193,
            25,
            100
        ]
    },
    {
        "ID": 26,
        "elevels": [
            2,
            0,
            6,
            2
        ],
        "epow": [
            95,
            75,
            125,
            95
        ],
        "eres": [
            48,
            7,
            127,
            48
        ]
    },
    {
        "ID": 27,
        "elevels": [
            2,
            0,
            6,
            2
        ],
        "epow": [
            95,
            75,
            125,
            95
        ],
        "eres": [
            100,
            25,
            193,
            100
        ]
    },
    {
        "ID": 28,
        "elevels": [
            0,
            2,
            2,
            6
        ],
        "epow": [
            80,
            95,
            95,
            120
        ],
        "eres": [
            7,
            48,
            48,
            127
        ]
    },
    {
        "ID": 29,
        "elevels": [
            0,
            2,
            2,
            6
        ],
        "epow": [
            80,
            95,
            95,
            120
        ],
        "eres": [
            25,
            100,
            100,
            193
        ]
    },
    {
        "ID": 30,
        "elevels": [
            3,
            2,
            2,
            2
        ],
        "epow": [
            100,
            85,
            85,
            85
        ],
        "eres": [
            100,
            72,
            72,
            48
        ]
    },
    {
        "ID": 31,
        "elevels": [
            3,
            2,
            2,
            2
        ],
        "epow": [
            100,
            85,
            85,
            85
        ],
        "eres": [
            127,
            100,
            100,
            72
        ]
    },
    {
        "ID": 32,
        "elevels": [
            2,
            3,
            2,
            2
        ],
        "epow": [
            85,
            100,
            85,
            85
        ],
        "eres": [
            72,
            100,
            48,
            72
        ]
    },
    {
        "ID": 33,
        "elevels": [
            2,
            3,
            2,
            2
        ],
        "epow": [
            85,
            100,
            85,
            85
        ],
        "eres": [
            100,
            127,
            72,
            100
        ]
    },
    {
        "ID": 34,
        "elevels": [
            2,
            2,
            3,
            2
        ],
        "epow": [
            85,
            85,
            100,
            85
        ],
        "eres": [
            72,
            48,
            100,
            72
        ]
    },
    {
        "ID": 35,
        "elevels": [
            2,
            2,
            3,
            2
        ],
        "epow": [
            85,
            85,
            100,
            85
        ],
        "eres": [
            100,
            72,
            127,
            100
        ]
    },
    {
        "ID": 36,
        "elevels": [
            2,
            2,
            2,
            3
        ],
        "epow": [
            85,
            85,
            85,
            100
        ],
        "eres": [
            48,
            72,
            72,
            100
        ]
    },
    {
        "ID": 37,
        "elevels": [
            2,
            2,
            2,
            3
        ],
        "epow": [
            85,
            85,
            85,
            100
        ],
        "eres": [
            72,
            100,
            100,
            127
        ]
    },
    {
        "ID": 38,
        "elevels": [
            3,
            3,
            0,
            4
        ],
        "epow": [
            95,
            100,
            75,
            105
        ],
        "eres": [
            100,
            127,
            25,
            152
        ]
    },
    {
        "ID": 39,
        "elevels": [
            7,
            5,
            10,
            7
        ],
        "epow": [
            100,
            90,
            110,
            100
        ],
        "eres": [
            100,
            72,
            175,
            127
        ]
    },
    {
        "ID": 40,
        "elevels": [
            8,
            6,
            11,
            8
        ],
        "epow": [
            100,
            95,
            105,
            100
        ],
        "eres": [
            127,
            72,
            175,
            100
        ]
    },
    {
        "ID": 41,
        "elevels": [
            9,
            7,
            14,
            9
        ],
        "epow": [
            100,
            95,
            110,
            100
        ],
        "eres": [
            127,
            72,
            175,
            127
        ]
    },
    {
        "ID": 42,
        "elevels": [
            4,
            8,
            6,
            5
        ],
        "epow": [
            100,
            130,
            120,
            110
        ],
        "eres": [
            72,
            193,
            127,
            152
        ]
    },
    {
        "ID": 43,
        "elevels": [
            0,
            2,
            1,
            4
        ],
        "epow": [
            90,
            95,
            95,
            110
        ],
        "eres": [
            152,
            110,
            72,
            48
        ]
    },
    {
        "ID": 44,
        "elevels": [
            14,
            16,
            13,
            15
        ],
        "epow": [
            90,
            105,
            85,
            95
        ],
        "eres": [
            130,
            180,
            72,
            150
        ]
    },
    {
        "ID": 45,
        "elevels": [
            11,
            7,
            14,
            9
        ],
        "epow": [
            95,
            85,
            105,
            95
        ],
        "eres": [
            100,
            60,
            175,
            100
        ]
    },
    {
        "ID": 46,
        "elevels": [
            17,
            14,
            12,
            10
        ],
        "epow": [
            110,
            100,
            100,
            100
        ],
        "eres": [
            150,
            190,
            130,
            110
        ]
    },
    {
        "ID": 47,
        "elevels": [
            18,
            11,
            15,
            8
        ],
        "epow": [
            110,
            100,
            105,
            95
        ],
        "eres": [
            190,
            130,
            175,
            98
        ]
    }
]